tk_nosy/__init__.py
tk_nosy/main_gui.py
tk_nosy/pyterps.py
tk_nosy/run_pytests.py
tk_nosy/select_py_version_dialog.py
tk_nosy/tk_nosy_popup.py
tk_nosy/tests/__init__.py
tk_nosy/tests/test_tk_nosy.py
tk_nosy-0.1.6.dist-info/DESCRIPTION.rst
tk_nosy-0.1.6.dist-info/METADATA
tk_nosy-0.1.6.dist-info/RECORD
tk_nosy-0.1.6.dist-info/WHEEL
tk_nosy-0.1.6.dist-info/entry_points.txt
tk_nosy-0.1.6.dist-info/metadata.json
tk_nosy-0.1.6.dist-info/top_level.txt
