Metadata-Version: 2.0
Name: tk-nosy
Version: 0.1.6
Summary: Tk_Nosy monitors project and unittest files and runs nosetests when they change.
Home-page: http://tk-nosy.readthedocs.org/en/latest/
Author: Charlie Taylor
Author-email: cet@appliedpython.com
License: GPL-3
Download-URL: https://github.com/sonofeft/Tk_Nosy
Keywords: tk_nosy setuptools development
Platform: any
Classifier: Development Status :: 3 - Alpha
Classifier: Operating System :: OS Independent
Classifier: Intended Audience :: Developers
Classifier: Intended Audience :: End Users/Desktop
Classifier: Topic :: Software Development :: Build Tools
Classifier: License :: OSI Approved :: GNU General Public License v3 (GPLv3)
Classifier: Programming Language :: Python :: 2
Classifier: Programming Language :: Python :: 2.7
Classifier: Programming Language :: Python :: 3
Classifier: Programming Language :: Python :: 3.3
Classifier: Programming Language :: Python :: 3.4
Requires-Dist: coverage
Requires-Dist: future
Requires-Dist: nose
